{"info": {}, "images": [{"id": 0, "file_name": "0.jpg", "height": 1080, "width": 1920}, {"id": 1, "file_name": "1020.jpg", "height": 1080, "width": 1920}, {"id": 2, "file_name": "1050.jpg", "height": 1080, "width": 1920}, {"id": 3, "file_name": "1080.jpg", "height": 1080, "width": 1920}, {"id": 4, "file_name": "1110.jpg", "height": 1080, "width": 1920}], "categories": [{"supercategory": "pedestrian", "id": 0, "name": "pedestrian"}], "annotations": [{"id": 0, "image_id": 0, "category_id": 0, "bbox": [376, 361, 40, 43], "area": 1720, "segmentation": [], "iscrowd": 0}, {"id": 1, "image_id": 1, "category_id": 0, "bbox": [1758, 278, 36, 42], "area": 1512, "segmentation": [], "iscrowd": 0}, {"id": 2, "image_id": 2, "category_id": 0, "bbox": [1191, 747, 36, 41], "area": 1476, "segmentation": [], "iscrowd": 0}, {"id": 3, "image_id": 3, "category_id": 0, "bbox": [1376, 830, 39, 35], "area": 1365, "segmentation": [], "iscrowd": 0}, {"id": 4, "image_id": 4, "category_id": 0, "bbox": [633, 809, 38, 41], "area": 1558, "segmentation": [], "iscrowd": 0}]}